parse_commit_gitdeps_xml/__init__.py
parse_commit_gitdeps_xml/blob.py
parse_commit_gitdeps_xml/commit_gitdeps_xml.py
parse_commit_gitdeps_xml/file.py
parse_commit_gitdeps_xml/hash.py
parse_commit_gitdeps_xml/pack.py
parse_commit_gitdeps_xml/stream_utils.py
parse_commit_gitdeps_xml-0.1.0.dist-info/LICENSE
parse_commit_gitdeps_xml-0.1.0.dist-info/METADATA
parse_commit_gitdeps_xml-0.1.0.dist-info/WHEEL
parse_commit_gitdeps_xml-0.1.0.dist-info/RECORD
