Metadata-Version: 2.1
Name: parse-commit-gitdeps-xml
Version: 0.1.0
Summary: Parse Commit.gitdeps.xml file
Author: sehnryr
Author-email: youn@melois.dev
Requires-Python: >=3.10,<4.0
Classifier: Programming Language :: Python :: 3
Classifier: Programming Language :: Python :: 3.10
Classifier: Programming Language :: Python :: 3.11
Classifier: Programming Language :: Python :: 3.12
